{"meta":{"name":"*Aventuras / Adventures","id":"ok464","type":"channel","posterShape":"landscape","videos":[{"id":"ok4stream_64_0","title":"Alpha - 2018"},{"id":"ok4stream_64_1","title":"A Wrinkle in Time - 2018"},{"id":"ok4stream_64_2","title":"Clash of the Titans - 1981"},{"id":"ok4stream_64_3","title":"Clash of the Titans - 2010"},{"id":"ok4stream_64_4","title":"De patitas a la calle (2020)"},{"id":"ok4stream_64_5","title":"Earth to Echo - 2014"},{"id":"ok4stream_64_6","title":"Exodus: Gods and Kings - 2014"},{"id":"ok4stream_64_7","title":"Fantastic Beasts: The Crimes of Grindelwald - 2018"},{"id":"ok4stream_64_8","title":"Goosebumps 2: Haunted Halloween - 2018"},{"id":"ok4stream_64_9","title":"Harry Potter and the Chamber of Secrets - 2002"},{"id":"ok4stream_64_10","title":"Harry Potter and the Deathly Hallows: Part 1 - 2010"},{"id":"ok4stream_64_11","title":"Harry Potter and the Deathly Hallows: Part 2 - 2011"},{"id":"ok4stream_64_12","title":"Harry Potter and the Goblet of Fire - 2005"},{"id":"ok4stream_64_13","title":"Harry Potter and the Half-Blood Prince - 2009"},{"id":"ok4stream_64_14","title":"Harry Potter and the Order of the Phoenix - 2007"},{"id":"ok4stream_64_15","title":"Harry Potter and the Philosopher's Stone - 2001"},{"id":"ok4stream_64_16","title":"Harry Potter and the Prisoner of Azkaban - 2004"},{"id":"ok4stream_64_17","title":"Holmes & Watson - 2018"},{"id":"ok4stream_64_18","title":"Indiana Jones and the Last Crusade - 1989"},{"id":"ok4stream_64_19","title":"Indiana Jones and the Temple of Doom - 1984"},{"id":"ok4stream_64_20","title":"Isle of Dogs - 2018"},{"id":"ok4stream_64_21","title":"Jumanji: The Next Level - 2019"},{"id":"ok4stream_64_22","title":"Jurassic World: Fallen Kingdom - 2018"},{"id":"ok4stream_64_23","title":"Knowing - 2009"},{"id":"ok4stream_64_24","title":"Maleficent - 2014"},{"id":"ok4stream_64_25","title":"Maze Runner: The Death Cure - 2018"},{"id":"ok4stream_64_26","title":"Mortal Engines - 2018"},{"id":"ok4stream_64_27","title":"Next Gen - 2018"},{"id":"ok4stream_64_28","title":"Ong Bak 2 - 2008"},{"id":"ok4stream_64_29","title":"Ong Bak: Muay Thai Warrior - 2003"},{"id":"ok4stream_64_30","title":"Pokémon: Mewtwo Strikes Back - Evolution - 2019"},{"id":"ok4stream_64_31","title":"Pokémon Detective Pikachu - 2019"},{"id":"ok4stream_64_32","title":"Pompeii - 2014"},{"id":"ok4stream_64_33","title":"Ready Player One - 2018"},{"id":"ok4stream_64_34","title":"Robin Hood - 1973"},{"id":"ok4stream_64_35","title":"Show Dogs - 2018"},{"id":"ok4stream_64_36","title":"Solo: A Star Wars Story - 2018"},{"id":"ok4stream_64_37","title":"Star Wars: The Rise of Skywalker - 2019"},{"id":"ok4stream_64_38","title":"Star Wars: The Rise of Skywalker - 2019"},{"id":"ok4stream_64_39","title":"The Aeronauts - 2019"},{"id":"ok4stream_64_40","title":"The Lord of the Rings: The Return of the King - 2003"},{"id":"ok4stream_64_41","title":"The Nutcracker and the Four Realms - 2018"},{"id":"ok4stream_64_42","title":"Tomb Raider - 2018"},{"id":"ok4stream_64_43","title":"Inkheart"},{"id":"ok4stream_64_44","title":"Secret Society of Second Born Royals"}]}}